py_messag_server-0.1.0.data/scripts/server_run
server/__init__.py
server/server.py
server/common/__init__.py
server/common/decorated.py
server/common/descriptrs.py
server/common/errors.py
server/common/metaclasses.py
server/common/utils.py
server/common/variables.py
server/logs/__init__.py
server/logs/config_server_log.py
server/server/__init__.py
server/server/add_user.py
server/server/config_window.py
server/server/core.py
server/server/database.py
server/server/main_window.py
server/server/remove_user.py
server/server/stat_window.py
server/unit_tests/__init__.py
server/unit_tests/test_client.py
server/unit_tests/test_server.py
server/unit_tests/test_utils.py
py_messag_server-0.1.0.dist-info/METADATA
py_messag_server-0.1.0.dist-info/WHEEL
py_messag_server-0.1.0.dist-info/top_level.txt
py_messag_server-0.1.0.dist-info/RECORD
